{"stats":{"minecraft:picked_up":{"minecraft:barrier":1,"minecraft:repeater":3,"minecraft:bedrock":1,"minecraft:stone_button":2,"minecraft:oak_sign":7,"minecraft:command_block":1,"minecraft:lever":3,"minecraft:snowball":1},"minecraft:custom":{"minecraft:time_since_rest":183871,"minecraft:sprint_one_cm":33984,"minecraft:walk_one_cm":249818,"minecraft:drop":3,"minecraft:inspect_hopper":70,"minecraft:fly_one_cm":280732,"minecraft:open_chest":5,"minecraft:crouch_one_cm":8431,"minecraft:play_time":328896,"minecraft:deaths":3,"minecraft:sneak_time":14155,"minecraft:walk_under_water_one_cm":13175,"minecraft:jump":524,"minecraft:walk_on_water_one_cm":278,"minecraft:leave_game":49,"minecraft:time_since_death":183846,"minecraft:total_world_time":724632},"minecraft:used":{"minecraft:redstone_torch":6,"minecraft:sticky_piston":15,"minecraft:lever":14,"minecraft:ender_eye":12,"minecraft:black_concrete":16,"minecraft:flint_and_steel":1,"minecraft:command_block":199,"minecraft:red_wool":34,"minecraft:red_concrete":6,"minecraft:dispenser":3,"minecraft:redstone":10,"minecraft:barrier":241,"minecraft:stone_button":6,"minecraft:oak_sign":97,"minecraft:chest":1,"minecraft:redstone_block":33,"minecraft:bedrock":119,"minecraft:sand":3,"minecraft:repeater":40,"minecraft:redstone_lamp":3,"minecraft:comparator":6,"minecraft:hopper":11,"minecraft:chain_command_block":112,"minecraft:yellow_concrete":15,"minecraft:repeating_command_block":13,"minecraft:end_portal_frame":14,"minecraft:oak_hanging_sign":10,"minecraft:observer":2,"minecraft:snowball":1,"minecraft:obsidian":16},"minecraft:dropped":{"minecraft:barrier":1,"minecraft:command_block":1,"minecraft:redstone":1}},"DataVersion":3463}